pyrspb/__init__.py
pyrspb/__main__.py
pyrspb/pyrspb.db
pyrspb/api/__init__.py
pyrspb/api/invention/__init__.py
pyrspb/api/invention/material_calculator.py
pyrspb/objects/__init__.py
pyrspb/objects/database.py
pyrspb/objects/page_parser.py
pyrspb/objects/invention/__init__.py
pyrspb/objects/invention/material.py
pyrspb/objects/invention/material_source.py
pyrspb/parsers/__init__.py
pyrspb/parsers/book/__init__.py
pyrspb/parsers/book/request_book_version.py
pyrspb/parsers/invention/__init__.py
pyrspb/parsers/invention/request_material_sources.py
pyrspb/parsers/invention/request_materials.py
pyrspb/utils/__init__.py
pyrspb/utils/string_formatting.py
pyrspb-0.0.2.3.dist-info/METADATA
pyrspb-0.0.2.3.dist-info/RECORD
pyrspb-0.0.2.3.dist-info/WHEEL
pyrspb-0.0.2.3.dist-info/top_level.txt
